{
    "captcha_1": null,
    "captcha_2": {
        "id": 2,
        "text": "Жжгр!ж",
        "success": null,
        "alternative_text": []
    },
    "captcha_3": {
        "id": 3,
        "text": "Прив",
        "success": null,
        "alternative_text": []
    },
    "captcha_4": {
        "id": 4,
        "text": "л8ж8т",
        "success": true,
        "alternative_text": []
    },
    "captcha_5": {
        "id": 5,
        "text": "ж94н8",
        "success": true,
        "alternative_text": []
    },
    "captcha_6": {
        "id": 6,
        "text": "лсг8б",
        "success": true,
        "alternative_text": []
    },
    "captcha_7": {
        "id": 7,
        "text": "лл7дк",
        "success": true,
        "alternative_text": []
    },
    "captcha_8": {
        "id": 8,
        "text": "жм64р",
        "success": true,
        "alternative_text": []
    },
    "captcha_9": {
        "id": 9,
        "text": "Жст48",
        "success": true,
        "alternative_text": []
    },
    "captcha_10": {
        "id": 10,
        "text": "жсмпм",
        "success": true,
        "alternative_text": []
    }
}